LICENSE
README.md
setup.py
grid_engine/__init__.py
grid_engine/__log__.py
grid_engine/__main__.py
grid_engine/_dungeon.py
grid_engine/_grid.py
grid_engine/_utility.py
grid_engine/_blueprint/__init__.py
grid_engine/_blueprint/__main__.py
grid_engine/_blueprint/_floorplan_classes.py
grid_engine/_blueprint/_floorplan_processing.py
grid_engine/_blueprint/_grid_blueprint.py
grid_engine/_blueprint/_grid_processing.py
grid_engine/_blueprint/_terrain_processing.py
grid_engine/_blueprint/objects.json
grid_engine/_blueprint/terrains.json
grid_engine/_cell/__init__.py
grid_engine/_cell/_cell.py
grid_engine/_grid_feature/__init__.py
grid_engine/_grid_feature/grid_feature.py
grid_engine/_grid_group/__init__.py
grid_engine/_grid_group/grid_group.py
grid_engine/_grid_object/__init__.py
grid_engine/_grid_object/grid_object.py
grid_engine/_grid_object/grid_item/__init__.py
grid_engine/_grid_object/grid_item/grid_item.py
grid_engine/_grid_object/grid_structure/__init__.py
grid_engine/_grid_object/grid_structure/grid_structure.py
grid_engine/_grid_object/grid_zone/__init__.py
grid_engine/_grid_object/grid_zone/grid_zone.py
grid_engine/_gui/__init__.py
grid_engine/_gui/_window/__init__.py
grid_engine/_gui/_window/_dialog.py
grid_engine/_gui/_window/_view.py
grid_engine/_gui/_window/_window.py
grid_engine/_terraform/__init__.py
grid_engine/_terraform/terraformer.py
gridengine_framework.egg-info/PKG-INFO
gridengine_framework.egg-info/SOURCES.txt
gridengine_framework.egg-info/dependency_links.txt
gridengine_framework.egg-info/requires.txt
gridengine_framework.egg-info/top_level.txt