Metadata-Version: 2.1
Name: gridengine-framework
Version: 0.91.6
Summary: A framework for generating and manipulating grid-based game worlds
Home-page: https://github.com/primal-coder/grid-engine
Author: James Evans
Author-email: joesaysahoy@gmail.com
Keywords: game development 2d grid world generation procedural generation cell numpy pillow pyglet pymunk cli
License-File: LICENSE
Requires-Dist: numpy
Requires-Dist: pillow
Requires-Dist: pyglet
Requires-Dist: pymunk
Requires-Dist: noise
